{
  "name": "magical",
  "symbol": "/'mædʒɪkl/",
  "chn": "adj. 有魔力的; 奇妙的",
  "example_en": "The forest looked magical under the moonlight.",
  "example_cn": "在月光下，森林看起来非常神奇。",
  "word_family": "magic (n.), magician (n.), magically (adv.)",
  "memory_tips": "词根 'magic' 来自希腊语 'mageia'，意为魔法。联想记忆：想象一个魔术师（magician）在舞台上表演，创造出奇妙（magical）的效果。图像记忆：想象一个充满星星和光芒的魔法棒，挥动时释放出五彩斑斓的光芒。",
  "difficulty": "2",
  "image_prompt": {
    "main_image": "一个夜晚的森林，月光透过树叶洒在地面上，营造出一种神秘而奇妙的氛围。",
    "example_image": "一个魔术师在舞台上挥动魔法棒，释放出五彩斑斓的光芒，观众们惊讶地看着这一切。"
  },
  "unit": 8,
  "audio": "magical.mp3",
  "audio_example": "magical_example.mp3",
  "image": "magical.png",
  "collocations": "magical moment (神奇的时刻); magical place (神奇的地方); magical power (魔力)"
}