{
  "word": "hard-working",
  "symbol": "/ˌhɑːd'wɜːkɪŋ/",
  "chn": "adj. 辛勤的",
  "example_en": "She is a hard-working student who always completes her assignments on time.",
  "example_cn": "她是一个勤奋的学生，总是按时完成作业。",
  "word_family": "hard work (n.), work hard (v.)",
  "memory_tips": "词根 'hard' 表示‘困难的’或‘努力的’，'working' 是‘工作’的现在分词形式。联想记忆：想象一个勤劳的蜜蜂在花丛中辛勤工作，帮助记忆‘辛勤的’含义。",
  "difficulty": "2",
  "image_prompt": {
    "main_image": "A cartoon bee diligently collecting pollen from flowers, symbolizing hard work and diligence.",
    "example_image": "A young student sitting at a desk, surrounded by books and a laptop, diligently working on her homework with a focused expression."
  },
  "unit": 5,
  "audio": "hard-working.mp3",
  "audio_example": "hard-working_example.mp3",
  "image": "hard-working.png"
}